img_resizer
