Metadata-Version: 1.1
Name: img-resizer
Version: 0.0.3
Summary: resize 3x image to @1x and @2x for iOS App
Home-page: https://github.com/g761007/img_resizer
Author: Daniel Hsieh
Author-email: a761007@gmail.com
License: MIT
Platform: UNKNOWN
Classifier: Environment :: Console
Classifier: Intended Audience :: Developers
Classifier: License :: OSI Approved :: MIT License
Classifier: Operating System :: OS Independent
Classifier: Programming Language :: Python
Classifier: Topic :: Utilities
Classifier: Topic :: Software Development :: Libraries :: Python Modules
